rjgtoys_yaml-0.0.2-py3.8-nspkg.pth
rjgtoys/yaml/__init__.py
rjgtoys_yaml-0.0.2.dist-info/LICENSE
rjgtoys_yaml-0.0.2.dist-info/METADATA
rjgtoys_yaml-0.0.2.dist-info/WHEEL
rjgtoys_yaml-0.0.2.dist-info/namespace_packages.txt
rjgtoys_yaml-0.0.2.dist-info/top_level.txt
rjgtoys_yaml-0.0.2.dist-info/RECORD
