Metadata-Version: 2.1
Name: rjgtoys-yaml
Version: 0.0.2
Summary: Reading and writing YAML
Home-page: https://github.com/bobgautier/rjgtoys-Yaml
Author: Robert J. Gautier
Author-email: bob.gautier@gmail.com
License: UNKNOWN
Platform: UNKNOWN
Classifier: Programming Language :: Python :: 3
Classifier: License :: OSI Approved :: MIT License
Classifier: Operating System :: OS Independent
Requires-Python: >=3.6
Requires-Dist: rjgtoys-thing
Requires-Dist: rjgtoys-xc
Requires-Dist: ruamel.yaml
